[
  {
    "number": "2082",
    "text": "One of the following writers is better known as \u00a0a playwright than as a novelist",
    "options": {
      "A": "C. Achebe",
      "B": "C. Ekwensi",
      "C": "W. Soyinka",
      "D": "J.P Clark"
    },
    "answer_url": "https://myschool.ng/classroom/literature-in-english/63191?exam_type=jamb&type=obj&page=417",
    "correct_answer": "C",
    "explanation": "click here\nThere is an explanation video availablebelow.",
    "year": "2022"
  },
  {
    "number": "2083",
    "text": "A narrative poem must",
    "options": {
      "A": "preach a sermon",
      "B": "tell a story",
      "C": "describe natural scenery",
      "D": "argue a question"
    },
    "answer_url": "https://myschool.ng/classroom/literature-in-english/63193?exam_type=jamb&type=obj&page=417",
    "correct_answer": "B",
    "explanation": "click here\nThere is an explanation video availablebelow.",
    "year": "2022"
  },
  {
    "number": "2084",
    "text": "Literature is studied as a subject at school \u00a0because",
    "options": {
      "A": "it exposes students to the realities of life",
      "B": "it provides entertainment",
      "C": "it merely gives additional work to students",
      "D": "it teaches the use of words"
    },
    "answer_url": "https://myschool.ng/classroom/literature-in-english/63195?exam_type=jamb&type=obj&page=417",
    "correct_answer": "A",
    "explanation": "click here\nThere is an explanation video availablebelow.",
    "year": "2022"
  },
  {
    "number": "2085",
    "text": "In The Flight to Australia', the following line occurs: 'Tier upon tier it towered, the terrible Apennines'. The figure of speech used in this line is known as",
    "options": {
      "A": "alliteration",
      "B": "litotes",
      "C": "exaggeration",
      "D": "parody"
    },
    "answer_url": "https://myschool.ng/classroom/literature-in-english/63198?exam_type=jamb&type=obj&page=417",
    "correct_answer": "A",
    "explanation": "click here\nThere is an explanation video availablebelow.",
    "year": "2022"
  },
  {
    "number": "2086",
    "text": "If we describe Kossoh Town Boy as an autobiography, we mean that it is",
    "options": {
      "A": "a historical novel",
      "B": "a piece of writing telling us about the Life of its author",
      "C": "a short story",
      "D": "a narrative tale"
    },
    "answer_url": "https://myschool.ng/classroom/literature-in-english/63201?exam_type=jamb&type=obj&page=418",
    "correct_answer": "B",
    "explanation": "click here\nThere is an explanation video availablebelow.",
    "year": "2022"
  },
  {
    "number": "2087",
    "text": "You cannot know\n\u00a0And should not bother\nTide and market come and go\nAnd so shall your\u00a0mother\n\nIn this verse the poet uses",
    "options": {
      "A": "alternate rhymes",
      "B": "monomyme",
      "C": "couplets",
      "D": "triplets"
    },
    "answer_url": "https://myschool.ng/classroom/literature-in-english/63203?exam_type=jamb&type=obj&page=418",
    "correct_answer": "A",
    "explanation": "There is an explanation video availablebelow.",
    "year": "2022"
  },
  {
    "number": "2088",
    "text": "Another shoal of cars swam past.\nOne, in particular, caught his eyes, a long slender thing,\nelegant as a swallow, all gleaming blue and silver;\na thousand guineas it would have cost, he thought.\nIn the first sentence, cars are described in terms of",
    "options": {
      "A": "birds",
      "B": "ants",
      "C": "fish",
      "D": "lampposts"
    },
    "answer_url": "https://myschool.ng/classroom/literature-in-english/63207?exam_type=jamb&type=obj&page=418",
    "correct_answer": "C",
    "explanation": "click here\nThere is an explanation video availablebelow.",
    "year": "2022"
  },
  {
    "number": "2089",
    "text": "Pick out the odd item",
    "options": {
      "A": "a Raisin in the Sun",
      "B": "Twelfth Night",
      "C": "Ozidi",
      "D": "The Concubine"
    },
    "answer_url": "https://myschool.ng/classroom/literature-in-english/63208?exam_type=jamb&type=obj&page=418",
    "correct_answer": "D",
    "explanation": "click here\nThere is an explanation video availablebelow.",
    "year": "2022"
  },
  {
    "number": "2090",
    "text": "That year the harvest was sad, like a funeral, and many farmers wept as they dug up the miserable yams. One man tied his cloth to a tree branch and hanged himself. The mood conveyed here is one of _____",
    "options": {
      "A": "excitement",
      "B": "sadness",
      "C": "joy",
      "D": "triumph"
    },
    "answer_url": "https://myschool.ng/classroom/literature-in-english/63211?exam_type=jamb&type=obj&page=418",
    "correct_answer": "B",
    "explanation": "The passage describes apoor harvestwhere \"many farmers wept\" and one man even \"hanged himself.\" These details create agloomy, sorrowful, and depressingatmosphere, which conveys a strong sense ofsadness.\nThere is an explanation video availablebelow.",
    "year": "2022"
  },
  {
    "number": "2091",
    "text": "One of the following terms applies to the discussion of both tragedy and comedy",
    "options": {
      "A": "climax",
      "B": "happy ending",
      "C": "tragic hero",
      "D": "alliteration"
    },
    "answer_url": "https://myschool.ng/classroom/literature-in-english/63213?exam_type=jamb&type=obj&page=419",
    "correct_answer": "A",
    "explanation": "click here\nThere is an explanation video availablebelow.",
    "year": "2022"
  },
  {
    "number": "2092",
    "text": "A character that is always against the interest of the protagonist is",
    "options": {
      "A": "hero",
      "B": "opposition",
      "C": "villain",
      "D": "heroine"
    },
    "answer_url": "https://myschool.ng/classroom/literature-in-english/67000?exam_type=jamb&type=obj&page=419",
    "correct_answer": "C",
    "explanation": "Villain reflects an opposing character in literature (antagonist).\nThere is an explanation video availablebelow.",
    "year": "2022"
  },
  {
    "number": "2093",
    "text": "The idea of metre as used in a literary piece is",
    "options": {
      "A": "stanza",
      "B": "rhythm",
      "C": "rhyme",
      "D": "verse"
    },
    "answer_url": "https://myschool.ng/classroom/literature-in-english/67001?exam_type=jamb&type=obj&page=419",
    "correct_answer": "B",
    "explanation": "Rhythm in poetry is marked by poetic metre.\nThere is an explanation video availablebelow.",
    "year": "2022"
  },
  {
    "number": "2094",
    "text": "A\u00a0hero whose weakness contributes to his downfall is called?",
    "options": {
      "A": "Deuteragonist",
      "B": "Periaktos",
      "C": "Tragic hero",
      "D": "Tragic flow"
    },
    "answer_url": "https://myschool.ng/classroom/literature-in-english/67002?exam_type=jamb&type=obj&page=419",
    "correct_answer": "C",
    "explanation": "A tragic hero is one whose weakness contributes to his downfall.\nThere is an explanation video availablebelow.",
    "year": "2022"
  },
  {
    "number": "2095",
    "text": "A travelogue is",
    "options": {
      "A": "a record of the writer's experience during a journey",
      "B": "the account of the experiences of an individual during his lifeline",
      "C": "the account of the travails of a character in a novel",
      "D": "a variant of a novel written in a free style on a writer's journey"
    },
    "answer_url": "https://myschool.ng/classroom/literature-in-english/67003?exam_type=jamb&type=obj&page=419",
    "correct_answer": "A",
    "explanation": "It is more or less a literary work about a journey.\nThere is an explanation video availablebelow.",
    "year": "2022"
  },
  {
    "number": "2096",
    "text": "A Literary work that ridicules the shortcomings of people or ideas is ......",
    "options": {
      "A": "a satire",
      "B": "a masque",
      "C": "a fable",
      "D": "an irony"
    },
    "answer_url": "https://myschool.ng/classroom/literature-in-english/67004?exam_type=jamb&type=obj&page=420",
    "correct_answer": "A",
    "explanation": "A satire ridicles people or ideas; points out their wrong in order for them to change for the better.\nThere is an explanation video availablebelow.",
    "year": "2022"
  },
  {
    "number": "2097",
    "text": "The exclusive right given to authors to protect their works from unlawful production is",
    "options": {
      "A": "a constitutional provision",
      "B": "a copyright",
      "C": "an authority to write",
      "D": "an author's right"
    },
    "answer_url": "https://myschool.ng/classroom/literature-in-english/67005?exam_type=jamb&type=obj&page=420",
    "correct_answer": "B",
    "explanation": "A copyright prevents other people from producing an intellectual work without the permission of the author.\nThere is an explanation video availablebelow.",
    "year": "2022"
  },
  {
    "number": "2098",
    "text": "Empathy is achieved when the audience",
    "options": {
      "A": "feels betrayed by the director",
      "B": "vicariously participates in the stage experience",
      "C": "attacks the character foil",
      "D": "denounces and humiliates the protagonist"
    },
    "answer_url": "https://myschool.ng/classroom/literature-in-english/67006?exam_type=jamb&type=obj&page=420",
    "correct_answer": "B",
    "explanation": "Empathy occurs when the audience shares in the stage experience. The audience in the theatre follows performance and simultaneously understands the feelings of the dramatis personae.\nThere is an explanation video availablebelow.",
    "year": "2022"
  },
  {
    "number": "2099",
    "text": "Mock-heroic poetry elevates",
    "options": {
      "A": "the important tales of heroes of the past era",
      "B": "trivial subject-matter by using the style of the classical epic",
      "C": "the stripping off of appearances in a witty manner",
      "D": "the beauty in human relationships as exemplified in Homer"
    },
    "answer_url": "https://myschool.ng/classroom/literature-in-english/67007?exam_type=jamb&type=obj&page=420",
    "correct_answer": "B",
    "explanation": "The mock-epic genre of poetry is one that uses the elevated and serious style of the epic to discuss trivial and unserious issues.\nThere is an explanation video availablebelow.",
    "year": "2022"
  },
  {
    "number": "2100",
    "text": "...... is also called a dynamic character",
    "options": {
      "A": "Protagonist",
      "B": "Round character",
      "C": "Flat character",
      "D": "Foil"
    },
    "answer_url": "https://myschool.ng/classroom/literature-in-english/67008?exam_type=jamb&type=obj&page=420",
    "correct_answer": "B",
    "explanation": "The reason is that a dynamic character changes with the event and action.\nThere is an explanation video availablebelow.",
    "year": "2022"
  },
  {
    "number": "2101",
    "text": "The subject matter of a literary work is the",
    "options": {
      "A": "plot",
      "B": "setting",
      "C": "theme",
      "D": "structure"
    },
    "answer_url": "https://myschool.ng/classroom/literature-in-english/67009?exam_type=jamb&type=obj&page=421",
    "correct_answer": "C",
    "explanation": "This is the major message in a literary work.\nThere is an explanation video availablebelow.",
    "year": "2022"
  },
  {
    "number": "2102",
    "text": "A dramatic type directed against an individual or a private institute with the intent to severely ridicule is called",
    "options": {
      "A": "lampoon",
      "B": "caricature",
      "C": "burlesque",
      "D": "satire"
    },
    "answer_url": "https://myschool.ng/classroom/literature-in-english/67010?exam_type=jamb&type=obj&page=421",
    "correct_answer": "A",
    "explanation": "A lampoon is a type of dramatic work, often in the form of writing, that aims to severely ridicule or mock an individual, group, or institution. It can be humorous, but its intent is to criticize or satirize in a harsh manner.\nThere is an explanation video availablebelow.",
    "year": "2022"
  },
  {
    "number": "2103",
    "text": "\"A time to sow,\nA time to reap,\nA time to born,\nA time to die\"\nThis exemplies the use of ...",
    "options": {
      "A": "hendiadys",
      "B": "chiasmus",
      "C": "anaphora",
      "D": "anadiplosis"
    },
    "answer_url": "https://myschool.ng/classroom/literature-in-english/67012?exam_type=jamb&type=obj&page=421",
    "correct_answer": "C",
    "explanation": "Anaphora is the repitition of a word or phrase at the beginning of each successive lines of poetry.\nThere is an explanation video availablebelow.",
    "year": "2022"
  },
  {
    "number": "2104",
    "text": "'I am jealous and passonate\nLike Jehovah, God of the Jews.'\nJ.P Clark: Olokun\nA device used in the second line of the excerpt above is",
    "options": {
      "A": "simile",
      "B": "paradox",
      "C": "metaphor",
      "D": "hyperbole"
    },
    "answer_url": "https://myschool.ng/classroom/literature-in-english/67013?exam_type=jamb&type=obj&page=421",
    "correct_answer": "A",
    "explanation": "The use of 'like' to compare two things of different class, but of the same attribute.\nThere is an explanation video availablebelow.",
    "year": "2022"
  },
  {
    "number": "2105",
    "text": "Dramatis personae in a play refers to",
    "options": {
      "A": "cast list",
      "B": "list of characters",
      "C": "protagonist and antagonist",
      "D": "order of appearance"
    },
    "answer_url": "https://myschool.ng/classroom/literature-in-english/67014?exam_type=jamb&type=obj&page=421",
    "correct_answer": "B",
    "explanation": "List of characters.\nThere is an explanation video availablebelow.",
    "year": "2022"
  },
  {
    "number": "2106",
    "text": "An irredeemable reversal of the hero's fortune in a tragedy is called.",
    "options": {
      "A": "purgation",
      "B": "peripeteia",
      "C": "hubris",
      "D": "anagnorisis"
    },
    "answer_url": "https://myschool.ng/classroom/literature-in-english/67015?exam_type=jamb&type=obj&page=422",
    "correct_answer": "B",
    "explanation": "Peripeteia is the reversal of fortune suffered by a tragic hero. It is believed that when a tragic character makes a mistake, such mistake must be punished. Therefore, the consequences of such becomes irredeemable.\nThere is an explanation video availablebelow.",
    "year": "2022"
  },
  {
    "number": "2107",
    "text": "\"I hate brave cowards like you\" is an example of",
    "options": {
      "A": "Irony",
      "B": "Antithesis",
      "C": "Eulogy",
      "D": "Oxymoron"
    },
    "answer_url": "https://myschool.ng/classroom/literature-in-english/67016?exam_type=jamb&type=obj&page=422",
    "correct_answer": "D",
    "explanation": "The reason is that there is the placement of two contradicting words placed side by side.\nThere is an explanation video availablebelow.",
    "year": "2022"
  },
  {
    "number": "2108",
    "text": "The narrator in a prose work who is also a character is",
    "options": {
      "A": "omniscient narrator",
      "B": "participatory narrator",
      "C": "objective narrator",
      "D": "subjective narrator"
    },
    "answer_url": "https://myschool.ng/classroom/literature-in-english/67018?exam_type=jamb&type=obj&page=422",
    "correct_answer": "B",
    "explanation": "Aparticipatory narratoris a narrator who is also a character in the story. This type of narrator shares experiences, thoughts\u00a0and actions from their own perspective, while also being involved in the events of the narrative. The story is told from the inside, as the narrator participates directly in the events being described.",
    "year": "2022"
  },
  {
    "number": "2109",
    "text": "\"Rays of sun peeping\u00a0through the cloud\u00a0\", the line is an example of",
    "options": {
      "A": "Synecdoche",
      "B": "Irony",
      "C": "Apostrophe",
      "D": "Personification"
    },
    "answer_url": "https://myschool.ng/classroom/literature-in-english/67019?exam_type=jamb&type=obj&page=422",
    "correct_answer": "D",
    "explanation": "click here\nThere is an explanation video availablebelow.",
    "year": "2022"
  },
  {
    "number": "2110",
    "text": "'To see a world in a grain of sand\nAnd a heaven in a wild flower\nHold infinity in the palm of your hand\nAnd eternity in an hour'\n- William Blake\nTo see a World In a Grain of Sand.\nThe predominant figure of speech used in the lines above is",
    "options": {
      "A": "metaphor",
      "B": "simile",
      "C": "paradox",
      "D": "hyperbole"
    },
    "answer_url": "https://myschool.ng/classroom/literature-in-english/67020?exam_type=jamb&type=obj&page=422",
    "correct_answer": "A",
    "explanation": "Every line is a metaphor \u2013 an imaginative way of describing something by referring to something else which is the same in a particular way.\nThere is an explanation video availablebelow.",
    "year": "2022"
  },
  {
    "number": "2111",
    "text": "\"I had not taken the first step in knowledge, I had not learnt to let go with the hands\".The above lines is an example of a",
    "options": {
      "A": "Aspotrophe",
      "B": "Alliteration",
      "C": "Repetitiion",
      "D": "Assonance"
    },
    "answer_url": "https://myschool.ng/classroom/literature-in-english/67021?exam_type=jamb&type=obj&page=423",
    "correct_answer": "C",
    "explanation": "The reason is that the same phrases are repeated at the beginning of each line.\nThere is an explanation video availablebelow.",
    "year": "2022"
  },
  {
    "number": "2112",
    "text": "Chanson\u00a0is a term denoting a",
    "options": {
      "A": "popular Korean verse",
      "B": "Song from the middle Ages",
      "C": "Form of love song",
      "D": "poem of Varied Metrical forms"
    },
    "answer_url": "https://myschool.ng/classroom/literature-in-english/67022?exam_type=jamb&type=obj&page=423",
    "correct_answer": "B",
    "explanation": "song with French lyrics, occurring from the Middle Ages\nThere is an explanation video availablebelow.",
    "year": "2022"
  },
  {
    "number": "2113",
    "text": "'The fair breeze blew\nThe white foam flew\nThe furrow followed free\nWe were the first that ever burst into that silent sea.'\n\nThe dominant figure of speech in the above passage is",
    "options": {
      "A": "repetition",
      "B": "alliteration",
      "C": "paradox",
      "D": "rhyme scheme"
    },
    "answer_url": "https://myschool.ng/classroom/literature-in-english/67023?exam_type=jamb&type=obj&page=423",
    "correct_answer": "B",
    "explanation": "Alliteration is the repetition of consonant sounds at the beginning of words in close proximity. In the passage, the repetition of the \"f\" sound in \"foam flew,\" and \"furrow followed free\", the repetition of the \"b\" sound in \"breeze blew\" and the repetition of the \"s\" sound in \"silent sea\"\u00a0\u00a0exemplifies alliteration. This technique creates a rhythmic and musical quality to the passage.\nThere is an explanation video availablebelow.",
    "year": "2022"
  },
  {
    "number": "2114",
    "text": "Which of these is the oldest genre of literature?",
    "options": {
      "A": "Poetry",
      "B": "Prose",
      "C": "Aroma",
      "D": "Drama"
    },
    "answer_url": "https://myschool.ng/classroom/literature-in-english/67024?exam_type=jamb&type=obj&page=423",
    "correct_answer": "A",
    "explanation": "Poetry is the oldest form of literature.\nThere is an explanation video availablebelow.",
    "year": "2022"
  },
  {
    "number": "2115",
    "text": "A device used by a writer to recall past event in a literary work is",
    "options": {
      "A": "anti-climax",
      "B": "interlude",
      "C": "flashback",
      "D": "foreshadowing"
    },
    "answer_url": "https://myschool.ng/classroom/literature-in-english/67025?exam_type=jamb&type=obj&page=423",
    "correct_answer": "C",
    "explanation": "Flash back. It brings events from the past to the moment.\nThere is an explanation video availablebelow.",
    "year": "2022"
  },
  {
    "number": "2116",
    "text": "The hunter dies\nand leaves his poverty to his gun\nThe blacksmith dies\nand leaves his poverty to his anvil...\nThe extract above is an example of",
    "options": {
      "A": "epic",
      "B": "eulogy",
      "C": "ballad",
      "D": "elegy"
    },
    "answer_url": "https://myschool.ng/classroom/literature-in-english/67026?exam_type=jamb&type=obj&page=424",
    "correct_answer": "D",
    "explanation": "More or less mourning the 'hunter' and 'the blacksmith'. Elegy is a poem written to mourn the dead.\nThere is an explanation video availablebelow.",
    "year": "2022"
  }
]