[
  {
    "number": "613",
    "text": "A poem consisting of fourteen lines is",
    "options": {
      "A": "a narrative",
      "B": "a sonnet",
      "C": "an ode",
      "D": "an elegy"
    },
    "answer_url": "https://myschool.ng/classroom/literature-in-english/39093?exam_type=waec&type=obj&page=123",
    "correct_answer": "B",
    "explanation": "Asonnetis a poem consisting of exactly fourteen lines, typically written in iambic pentameter. Sonnets often follow specific rhyme schemes and are usually associated with themes of love, nature or reflection.\nA narrativeis a poem that tells a story, regardless of its length.An odeis a type of lyrical poem that is usually longer and praises something or someone.An elegyis a mournful poem, often lamenting someone's death, but it can be of varying lengths.",
    "year": "2009"
  },
  {
    "number": "614",
    "text": "The attitude of a writer towards the subject matter is the",
    "options": {
      "A": "tone",
      "B": "plot",
      "C": "crisis",
      "D": "climax"
    },
    "answer_url": "https://myschool.ng/classroom/literature-in-english/39094?exam_type=waec&type=obj&page=123",
    "correct_answer": "A",
    "explanation": "click here",
    "year": "2009"
  },
  {
    "number": "615",
    "text": "The pattern of end rhymes in a poem is called",
    "options": {
      "A": "internal rhyme",
      "B": "rhyme scheme",
      "C": "rhythm",
      "D": "scansion"
    },
    "answer_url": "https://myschool.ng/classroom/literature-in-english/39095?exam_type=waec&type=obj&page=123",
    "correct_answer": "B",
    "explanation": "click here",
    "year": "2009"
  },
  {
    "number": "616",
    "text": "The most exciting and tense part of a story is the",
    "options": {
      "A": "epilogue",
      "B": "climax",
      "C": "prologue",
      "D": "exposition"
    },
    "answer_url": "https://myschool.ng/classroom/literature-in-english/39096?exam_type=waec&type=obj&page=124",
    "correct_answer": "B",
    "explanation": "click here",
    "year": "2009"
  },
  {
    "number": "617",
    "text": "Lines of unrhymed poetry are known as",
    "options": {
      "A": "blank verse",
      "B": "assonance",
      "C": "consonance",
      "D": "free verse"
    },
    "answer_url": "https://myschool.ng/classroom/literature-in-english/39099?exam_type=waec&type=obj&page=124",
    "correct_answer": "A",
    "explanation": "Blank verse refers tounrhymed poetry written in iambic pentameter. It has a regular meter but does not rhyme. This form is commonly used in Shakespearean plays and other classical literature. A free verse, on the other hand, is poetry that does not follow a fixed meter or rhyme scheme, unlike blank verse, which has a defined meter.",
    "year": "2009"
  },
  {
    "number": "618",
    "text": "A dramatic performance with only bodily movements and without words is",
    "options": {
      "A": "a mime",
      "B": "an aside",
      "C": "a soliloquy",
      "D": "an opera"
    },
    "answer_url": "https://myschool.ng/classroom/literature-in-english/39100?exam_type=waec&type=obj&page=124",
    "correct_answer": "A",
    "explanation": "click here",
    "year": "2009"
  },
  {
    "number": "619",
    "text": "''Mathematics is my Achilles' heel'' is an example of",
    "options": {
      "A": "litotes",
      "B": "metonymy",
      "C": "allusion",
      "D": "analogy"
    },
    "answer_url": "https://myschool.ng/classroom/literature-in-english/39102?exam_type=waec&type=obj&page=124",
    "correct_answer": "C",
    "explanation": "Anallusionis a figure of speech that makes a reference to a well-known person, place, event, literary work\u00a0or myth. In the phrase\"Mathematics is my Achilles' heel,\"there is a reference toAchilles, a Greek mythological hero who had only one weakness\u2014his heel. This suggests that mathematics is the speaker\u2019s main weakness.",
    "year": "2009"
  },
  {
    "number": "620",
    "text": "A short poem lamenting the death of someone is a",
    "options": {
      "A": "lyric",
      "B": "sonnet",
      "C": "ballad",
      "D": "threnody"
    },
    "answer_url": "https://myschool.ng/classroom/literature-in-english/39103?exam_type=waec&type=obj&page=124",
    "correct_answer": "D",
    "explanation": "Threnody is a wailing ode, song, hymn or poem\u00a0of mourning composed or performed as a memorial to a dead person",
    "year": "2009"
  },
  {
    "number": "621",
    "text": "In a story, the adversary of the protagonist is the",
    "options": {
      "A": "hero",
      "B": "heroine",
      "C": "antagonist",
      "D": "foil"
    },
    "answer_url": "https://myschool.ng/classroom/literature-in-english/39107?exam_type=waec&type=obj&page=125",
    "correct_answer": "C",
    "explanation": "click here",
    "year": "2009"
  },
  {
    "number": "622",
    "text": "''Tell me not, sweet, I  am unkind'' illustrates",
    "options": {
      "A": "inversion",
      "B": "paradox",
      "C": "humour",
      "D": "mood"
    },
    "answer_url": "https://myschool.ng/classroom/literature-in-english/39109?exam_type=waec&type=obj&page=125",
    "correct_answer": "A",
    "explanation": "click here",
    "year": "2009"
  },
  {
    "number": "623",
    "text": "The art of giving human attributes to non-human objects is",
    "options": {
      "A": "personification",
      "B": "allegory",
      "C": "anecdote",
      "D": "allusion"
    },
    "answer_url": "https://myschool.ng/classroom/literature-in-english/39111?exam_type=waec&type=obj&page=125",
    "correct_answer": "A",
    "explanation": "click here",
    "year": "2009"
  },
  {
    "number": "624",
    "text": "A long narrative poem which deals with heroic deeds is",
    "options": {
      "A": "lyric",
      "B": "epic",
      "C": "ode",
      "D": "euphony"
    },
    "answer_url": "https://myschool.ng/classroom/literature-in-english/39112?exam_type=waec&type=obj&page=125",
    "correct_answer": "B",
    "explanation": "click here",
    "year": "2009"
  },
  {
    "number": "625",
    "text": "A poem of four lines is called",
    "options": {
      "A": "quatrain",
      "B": "sestet",
      "C": "sonnet",
      "D": "couplet"
    },
    "answer_url": "https://myschool.ng/classroom/literature-in-english/39113?exam_type=waec&type=obj&page=125",
    "correct_answer": "A",
    "explanation": "click here",
    "year": "2009"
  },
  {
    "number": "626",
    "text": "A literary piece used to mock of ridicule a society or practice is called",
    "options": {
      "A": "an allegory",
      "B": "a fable",
      "C": "a farce",
      "D": "a satire"
    },
    "answer_url": "https://myschool.ng/classroom/literature-in-english/39116?exam_type=waec&type=obj&page=126",
    "correct_answer": "D",
    "explanation": "click here",
    "year": "2009"
  },
  {
    "number": "627",
    "text": "The story of a person's life written by another is",
    "options": {
      "A": "history",
      "B": "autobiography",
      "C": "biography",
      "D": "anthology"
    },
    "answer_url": "https://myschool.ng/classroom/literature-in-english/39117?exam_type=waec&type=obj&page=126",
    "correct_answer": "C",
    "explanation": "click here",
    "year": "2009"
  },
  {
    "number": "628",
    "text": "A folktale is a",
    "options": {
      "A": "novel",
      "B": "work of ficion",
      "C": "biography",
      "D": "novelette"
    },
    "answer_url": "https://myschool.ng/classroom/literature-in-english/39121?exam_type=waec&type=obj&page=126",
    "correct_answer": "B",
    "explanation": "click here",
    "year": "2009"
  },
  {
    "number": "629",
    "text": "A poem written in an elaborate style to address or celebrate an object or event is called",
    "options": {
      "A": "a ballad",
      "B": "an epic",
      "C": "a dirge",
      "D": "an ode"
    },
    "answer_url": "https://myschool.ng/classroom/literature-in-english/39125?exam_type=waec&type=obj&page=126",
    "correct_answer": "D",
    "explanation": "click here",
    "year": "2009"
  },
  {
    "number": "630",
    "text": "The dominant device in the above lines is",
    "options": {
      "A": "burlesque",
      "B": "paradox",
      "C": "conflict",
      "D": "irony."
    },
    "answer_url": "https://myschool.ng/classroom/literature-in-english/39129?exam_type=waec&type=obj&page=126",
    "correct_answer": "D",
    "explanation": "click here",
    "year": "2009"
  },
  {
    "number": "631",
    "text": "The tone of the poem is one of",
    "options": {
      "A": "sorrow",
      "B": "sarcasm",
      "C": "happiness",
      "D": "anger"
    },
    "answer_url": "https://myschool.ng/classroom/literature-in-english/39132?exam_type=waec&type=obj&page=127",
    "correct_answer": "B",
    "explanation": "click here",
    "year": "2009"
  },
  {
    "number": "632",
    "text": "Kyeiwa is",
    "options": {
      "A": "relaxed",
      "B": "ecstatic",
      "C": "frightened",
      "D": "elated"
    },
    "answer_url": "https://myschool.ng/classroom/literature-in-english/39152?exam_type=waec&type=obj&page=127",
    "correct_answer": "D",
    "explanation": "click here",
    "year": "2009"
  },
  {
    "number": "633",
    "text": "The narrative technique is",
    "options": {
      "A": "third person",
      "B": "a soliloquy",
      "C": "first person",
      "D": "an aside"
    },
    "answer_url": "https://myschool.ng/classroom/literature-in-english/39172?exam_type=waec&type=obj&page=127",
    "correct_answer": "A",
    "explanation": "click here",
    "year": "2009"
  },
  {
    "number": "634",
    "text": "The passage is",
    "options": {
      "A": "expository",
      "B": "argumentative",
      "C": "narrative",
      "D": "analytical"
    },
    "answer_url": "https://myschool.ng/classroom/literature-in-english/39173?exam_type=waec&type=obj&page=127",
    "correct_answer": "C",
    "explanation": "click here",
    "year": "2009"
  },
  {
    "number": "635",
    "text": "The atmosphere in the passage is one of",
    "options": {
      "A": "love",
      "B": "fear",
      "C": "anger",
      "D": "joy"
    },
    "answer_url": "https://myschool.ng/classroom/literature-in-english/39174?exam_type=waec&type=obj&page=127",
    "correct_answer": "B",
    "explanation": "This is evident from phrases like \"clinging to metal support,\" \"petrified,\" and the description of the journey at \"breakneck speed,\" which all suggest a tense and fearful atmosphere.",
    "year": "2009"
  },
  {
    "number": "636",
    "text": "\"The little vehicle laps up the distance'' conveys the impression of",
    "options": {
      "A": "leizure",
      "B": "pleasure",
      "C": "strength",
      "D": "speed"
    },
    "answer_url": "https://myschool.ng/classroom/literature-in-english/39175?exam_type=waec&type=obj&page=128",
    "correct_answer": "D",
    "explanation": "click here",
    "year": "2009"
  },
  {
    "number": "637",
    "text": "The poem is about",
    "options": {
      "A": "war",
      "B": "dirt",
      "C": "travelling",
      "D": "prison life"
    },
    "answer_url": "https://myschool.ng/classroom/literature-in-english/39176?exam_type=waec&type=obj&page=128",
    "correct_answer": "D",
    "explanation": "click here",
    "year": "2009"
  },
  {
    "number": "638",
    "text": "The imagery in the first four lines is predominantly",
    "options": {
      "A": "agricultural",
      "B": "military",
      "C": "political",
      "D": "social"
    },
    "answer_url": "https://myschool.ng/classroom/literature-in-english/39177?exam_type=waec&type=obj&page=128",
    "correct_answer": "B",
    "explanation": "click here",
    "year": "2009"
  },
  {
    "number": "639",
    "text": "''....a thousand miles'' is an example of",
    "options": {
      "A": "hyperbole",
      "B": "irony",
      "C": "antithesis",
      "D": "epigram"
    },
    "answer_url": "https://myschool.ng/classroom/literature-in-english/39178?exam_type=waec&type=obj&page=128",
    "correct_answer": "A",
    "explanation": "click here",
    "year": "2009"
  },
  {
    "number": "640",
    "text": "The poem is written in",
    "options": {
      "A": "blank verse",
      "B": "pentameter",
      "C": "free verse",
      "D": "trochee"
    },
    "answer_url": "https://myschool.ng/classroom/literature-in-english/39179?exam_type=waec&type=obj&page=128",
    "correct_answer": "C",
    "explanation": "click here",
    "year": "2009"
  },
  {
    "number": "641",
    "text": "The impression created of the persona is one of",
    "options": {
      "A": "anger",
      "B": "competitiveness",
      "C": "reconciliation",
      "D": "resignation"
    },
    "answer_url": "https://myschool.ng/classroom/literature-in-english/39180?exam_type=waec&type=obj&page=129",
    "correct_answer": "C",
    "explanation": "click here",
    "year": "2009"
  },
  {
    "number": "642",
    "text": "The speaker is",
    "options": {
      "A": "Polonius",
      "B": "Reynaldo",
      "C": "Rosencrantz",
      "D": "Laertes"
    },
    "answer_url": "https://myschool.ng/classroom/literature-in-english/39183?exam_type=waec&type=obj&page=129",
    "correct_answer": "D",
    "explanation": "click here",
    "year": "2009"
  },
  {
    "number": "643",
    "text": "A character being addressed is",
    "options": {
      "A": "Ophelia",
      "B": "Hamlet",
      "C": "Marcellus",
      "D": "Bernado"
    },
    "answer_url": "https://myschool.ng/classroom/literature-in-english/39186?exam_type=waec&type=obj&page=129",
    "correct_answer": "A",
    "explanation": "click here",
    "year": "2009"
  },
  {
    "number": "644",
    "text": "The subject of discussion is",
    "options": {
      "A": "Horatio",
      "B": "Hamlet",
      "C": "Marcellus",
      "D": "Bernado"
    },
    "answer_url": "https://myschool.ng/classroom/literature-in-english/39187?exam_type=waec&type=obj&page=129",
    "correct_answer": "B",
    "explanation": "click here",
    "year": "2009"
  },
  {
    "number": "645",
    "text": "The speaker is",
    "options": {
      "A": "happy",
      "B": "confused",
      "C": "excited",
      "D": "anxious"
    },
    "answer_url": "https://myschool.ng/classroom/literature-in-english/39188?exam_type=waec&type=obj&page=129",
    "correct_answer": "A",
    "explanation": "click here",
    "year": "2009"
  },
  {
    "number": "646",
    "text": "Thews and bulk means",
    "options": {
      "A": "power",
      "B": "body and soul",
      "C": "strength and size",
      "D": "brain"
    },
    "answer_url": "https://myschool.ng/classroom/literature-in-english/39190?exam_type=waec&type=obj&page=130",
    "correct_answer": "B",
    "explanation": "click here",
    "year": "2009"
  },
  {
    "number": "647",
    "text": "Speaker X is",
    "options": {
      "A": "Horatio",
      "B": "Marcellus",
      "C": "Hamlet",
      "D": "Laertes"
    },
    "answer_url": "https://myschool.ng/classroom/literature-in-english/39191?exam_type=waec&type=obj&page=130",
    "correct_answer": "B",
    "explanation": "click here",
    "year": "2009"
  },
  {
    "number": "648",
    "text": "The setting is",
    "options": {
      "A": "another part of the platform",
      "B": "a platform in front of the castle",
      "C": "the queen's palace",
      "D": "a room in the castle"
    },
    "answer_url": "https://myschool.ng/classroom/literature-in-english/39192?exam_type=waec&type=obj&page=130",
    "correct_answer": "B",
    "explanation": "click here",
    "year": "2009"
  },
  {
    "number": "649",
    "text": "The atmosphere is",
    "options": {
      "A": "frightening",
      "B": "peaceful",
      "C": "relaxed",
      "D": "bleak"
    },
    "answer_url": "https://myschool.ng/classroom/literature-in-english/39193?exam_type=waec&type=obj&page=130",
    "correct_answer": "A",
    "explanation": "click here",
    "year": "2009"
  },
  {
    "number": "650",
    "text": "Tis gone and will not answer refers to the",
    "options": {
      "A": "gravedigger",
      "B": "ghost",
      "C": "servant",
      "D": "soldier"
    },
    "answer_url": "https://myschool.ng/classroom/literature-in-english/39195?exam_type=waec&type=obj&page=130",
    "correct_answer": "B",
    "explanation": "click here",
    "year": "2009"
  },
  {
    "number": "651",
    "text": "Speaker Y is",
    "options": {
      "A": "Bernado",
      "B": "Francisco",
      "C": "Polonius",
      "D": "Rosencrantz"
    },
    "answer_url": "https://myschool.ng/classroom/literature-in-english/39196?exam_type=waec&type=obj&page=131",
    "correct_answer": "A",
    "explanation": "click here",
    "year": "2009"
  },
  {
    "number": "652",
    "text": "The speaker is",
    "options": {
      "A": "the king",
      "B": "Laertes",
      "C": "the queen",
      "D": "polonius"
    },
    "answer_url": "https://myschool.ng/classroom/literature-in-english/39202?exam_type=waec&type=obj&page=131",
    "correct_answer": "C",
    "explanation": "click here",
    "year": "2009"
  },
  {
    "number": "653",
    "text": "After this speech, the speaker",
    "options": {
      "A": "exits",
      "B": "dies",
      "C": "wakes up",
      "D": "sleeps off"
    },
    "answer_url": "https://myschool.ng/classroom/literature-in-english/39203?exam_type=waec&type=obj&page=131",
    "correct_answer": "A",
    "explanation": "click here",
    "year": "2009"
  },
  {
    "number": "654",
    "text": "The character being addressed is",
    "options": {
      "A": "Laertes",
      "B": "Hamlet",
      "C": "Polonius",
      "D": "Ophelia"
    },
    "answer_url": "https://myschool.ng/classroom/literature-in-english/39209?exam_type=waec&type=obj&page=131",
    "correct_answer": "D",
    "explanation": "click here",
    "year": "2009"
  },
  {
    "number": "655",
    "text": "Another character present on the scene is",
    "options": {
      "A": "Rosencrantz",
      "B": "Guildenstern",
      "C": "Polonius",
      "D": "Hamlet"
    },
    "answer_url": "https://myschool.ng/classroom/literature-in-english/39211?exam_type=waec&type=obj&page=131",
    "correct_answer": "C",
    "explanation": "click here",
    "year": "2009"
  },
  {
    "number": "656",
    "text": "The wildness referred to can also be called",
    "options": {
      "A": "love",
      "B": "madness",
      "C": "happiness",
      "D": "death"
    },
    "answer_url": "https://myschool.ng/classroom/literature-in-english/39212?exam_type=waec&type=obj&page=132",
    "correct_answer": "A",
    "explanation": "This extract is fromShakespeare\u2019sHamlet(Act 3, Scene 1). The speaker isGertrude, Hamlet\u2019s mother, addressingOphelia.\nGertrude hopes thatOphelia\u2019s beautywill be the reason forHamlet\u2019s \"wildness\" (his erratic behavior and madness).She also expresses hope that Ophelia\u2019svirtuewill help Hamlet return to his\"wonted way\" (normal self).The \"wildness\" here refers toHamlet\u2019s madness, which is a major theme in the play\u2014whether it is real or feigned.",
    "year": "2009"
  },
  {
    "number": "657",
    "text": "Speaker H is",
    "options": {
      "A": "Fortunbras",
      "B": "Horatio",
      "C": "Osric",
      "D": "Ambassador"
    },
    "answer_url": "https://myschool.ng/classroom/literature-in-english/39221?exam_type=waec&type=obj&page=132",
    "correct_answer": "A",
    "explanation": "click here",
    "year": "2009"
  },
  {
    "number": "658",
    "text": "Speaker l is",
    "options": {
      "A": "Horatio",
      "B": "Claudius",
      "C": "Hamlet",
      "D": "Osric"
    },
    "answer_url": "https://myschool.ng/classroom/literature-in-english/39222?exam_type=waec&type=obj&page=132",
    "correct_answer": "A",
    "explanation": "click here",
    "year": "2009"
  },
  {
    "number": "659",
    "text": "sight refers to",
    "options": {
      "A": "players and drummers",
      "B": "soldiers from England",
      "C": "incest committed",
      "D": "dead bodies"
    },
    "answer_url": "https://myschool.ng/classroom/literature-in-english/39223?exam_type=waec&type=obj&page=132",
    "correct_answer": "D",
    "explanation": "click here",
    "year": "2009"
  },
  {
    "number": "660",
    "text": "Shortly before this speech, _ died",
    "options": {
      "A": "the king",
      "B": "the queen",
      "C": "Hamlet",
      "D": "Polonius"
    },
    "answer_url": "https://myschool.ng/classroom/literature-in-english/39224?exam_type=waec&type=obj&page=132",
    "correct_answer": "C",
    "explanation": "click here",
    "year": "2009"
  },
  {
    "number": "661",
    "text": "Other characters who died earlier were",
    "options": {
      "A": "the queen and ambassador",
      "B": "Hamlet and Osric",
      "C": "Ophelia and Horatio",
      "D": "Laertes and the King"
    },
    "answer_url": "https://myschool.ng/classroom/literature-in-english/39225?exam_type=waec&type=obj&page=133",
    "correct_answer": "D",
    "explanation": "click here",
    "year": "2009"
  }
]